astroemperor/__init__.py
astroemperor/additional_kernels.py
astroemperor/block_repo.py
astroemperor/canvas.py
astroemperor/emp.py
astroemperor/emp_model.py
astroemperor/globals.py
astroemperor/math_utils.py
astroemperor/param_repo.py
astroemperor/qol_utils.py
astroemperor/support/endit_dynesty.scr
astroemperor/support/endit_freeze.scr
astroemperor/support/endit_freeze1.scr
astroemperor/support/endit_reddemcee.scr
astroemperor/support/init_dynesty.scr
astroemperor/support/init_reddemcee.scr
astroemperor/support/run_main.scr
astroemperor/support/save_metadata.scr
astroemperor/support/PAE/00.pae
astroemperor/support/PAE/01.pae
astroemperor/support/PAE/02.pae
astroemperor/support/PAE/03.pae
astroemperor/support/PAE/04.pae
astroemperor/support/PAE/06.pae
astroemperor/support/astrometry/astrometry.plot
astroemperor/support/astrometry/constants.scr
astroemperor/support/astrometry/plot.00
astroemperor/support/astrometry/plot.01
astroemperor/support/deadtime/astrometric_gaps_gaiadr2_08252020.csv
astroemperor/support/deadtime/astrometric_gaps_gaiaedr3_12232020.csv
astroemperor/support/kernels/00.kernel
astroemperor/support/kernels/00plot.kernel
astroemperor/support/kernels/01.kernel
astroemperor/support/kernels/saved_before_q2.kernel
astroemperor/support/likelihoods/00.like
astroemperor/support/likelihoods/02.like
astroemperor/support/likelihoods/a00.like
astroemperor/support/likelihoods/a00_k2.like
astroemperor/support/likelihoods/a01.like
astroemperor/support/models/acc.model
astroemperor/support/models/akep00.model
astroemperor/support/models/am_jitter00.model
astroemperor/support/models/am_offset00.model
astroemperor/support/models/empty.model
astroemperor/support/models/ins00.model
astroemperor/support/models/ins01 (copy).model
astroemperor/support/models/ins01.model
astroemperor/support/models/ins02.model
astroemperor/support/models/ins03 (copy).model
astroemperor/support/models/ins03.model
astroemperor/support/models/jitter00.model
astroemperor-1.0.1.dist-info/licenses/LICENSE
astroemperor-1.0.1.dist-info/METADATA
astroemperor-1.0.1.dist-info/WHEEL
astroemperor-1.0.1.dist-info/top_level.txt
astroemperor-1.0.1.dist-info/RECORD
