Metadata-Version: 2.4
Name: astroemperor
Version: 1.0.1
Summary: Flexible python exoplanet fitter
Author-email: ReddTea <redd@tea.com>
License: MIT License
Project-URL: Homepage, https://astroemperor.readthedocs.io/
Project-URL: Documentation, https://astroemperor.readthedocs.io/
Project-URL: Repository, https://github.com/ReddTea/astroemperor/
Project-URL: Issues, https://github.com/ReddTea/astroemperor/issues
Keywords: python,MCMC,sampler,adaptive,parallel tempering
Classifier: Programming Language :: Python :: 3
Classifier: License :: OSI Approved :: MIT License
Classifier: Operating System :: OS Independent
Requires-Python: >=3.6
License-File: LICENSE
Requires-Dist: matplotlib>=3.5.1
Requires-Dist: pandas
Requires-Dist: scikit-learn
Requires-Dist: kepler.py
Requires-Dist: reddemcee
Requires-Dist: h5py
Requires-Dist: reddcolors
Requires-Dist: tabulate
Requires-Dist: termcolor
Requires-Dist: tqdm
Requires-Dist: corner
Requires-Dist: fast_kepler
Dynamic: license-file
